{
  "date": "2026-03-03",
  "rates": [
    {
      "currency": "USD",
      "currencyZhTw": "美金",
      "cashBuying": "31.095",
      "cashSelling": "31.765",
      "sightBuying": "31.445",
      "sightSelling": "31.545"
    },
    {
      "currency": "HKD",
      "currencyZhTw": "港幣",
      "cashBuying": "3.87",
      "cashSelling": "4.074",
      "sightBuying": "3.996",
      "sightSelling": "4.056"
    },
    {
      "currency": "GBP",
      "currencyZhTw": "英鎊",
      "cashBuying": "41.08",
      "cashSelling": "43.2",
      "sightBuying": "42.09",
      "sightSelling": "42.49"
    },
    {
      "currency": "AUD",
      "currencyZhTw": "澳幣",
      "cashBuying": "22.03",
      "cashSelling": "22.81",
      "sightBuying": "22.32",
      "sightSelling": "22.52"
    },
    {
      "currency": "CAD",
      "currencyZhTw": "加拿大幣",
      "cashBuying": "22.56",
      "cashSelling": "23.47",
      "sightBuying": "22.96",
      "sightSelling": "23.16"
    },
    {
      "currency": "SGD",
      "currencyZhTw": "新加坡幣",
      "cashBuying": "24.2",
      "cashSelling": "25.11",
      "sightBuying": "24.69",
      "sightSelling": "24.87"
    },
    {
      "currency": "CHF",
      "currencyZhTw": "瑞士法郎",
      "cashBuying": "39.62",
      "cashSelling": "40.82",
      "sightBuying": "40.3",
      "sightSelling": "40.55"
    },
    {
      "currency": "JPY",
      "currencyZhTw": "日圓",
      "cashBuying": "0.1909",
      "cashSelling": "0.2037",
      "sightBuying": "0.1982",
      "sightSelling": "0.2022"
    },
    {
      "currency": "ZAR",
      "currencyZhTw": "南非幣",
      "cashBuying": "-",
      "cashSelling": "-",
      "sightBuying": "1.92",
      "sightSelling": "2"
    },
    {
      "currency": "SEK",
      "currencyZhTw": "瑞典幣",
      "cashBuying": "-",
      "cashSelling": "-",
      "sightBuying": "3.4",
      "sightSelling": "3.5"
    },
    {
      "currency": "NZD",
      "currencyZhTw": "紐元",
      "cashBuying": "18.27",
      "cashSelling": "19.12",
      "sightBuying": "18.65",
      "sightSelling": "18.85"
    },
    {
      "currency": "THB",
      "currencyZhTw": "泰幣",
      "cashBuying": "0.8747",
      "cashSelling": "1.0647",
      "sightBuying": "0.9881",
      "sightSelling": "1.0281"
    },
    {
      "currency": "PHP",
      "currencyZhTw": "菲國比索",
      "cashBuying": "0.4751",
      "cashSelling": "0.6071",
      "sightBuying": "-",
      "sightSelling": "-"
    },
    {
      "currency": "IDR",
      "currencyZhTw": "印尼幣",
      "cashBuying": "0.00153",
      "cashSelling": "0.00223",
      "sightBuying": "-",
      "sightSelling": "-"
    },
    {
      "currency": "EUR",
      "currencyZhTw": "歐元",
      "cashBuying": "36.05",
      "cashSelling": "37.39",
      "sightBuying": "36.67",
      "sightSelling": "37.07"
    },
    {
      "currency": "KRW",
      "currencyZhTw": "韓元",
      "cashBuying": "0.01981",
      "cashSelling": "0.02371",
      "sightBuying": "-",
      "sightSelling": "-"
    },
    {
      "currency": "VND",
      "currencyZhTw": "越南盾",
      "cashBuying": "0.00098",
      "cashSelling": "0.00139",
      "sightBuying": "-",
      "sightSelling": "-"
    },
    {
      "currency": "MYR",
      "currencyZhTw": "馬來幣",
      "cashBuying": "6.995",
      "cashSelling": "8.52",
      "sightBuying": "-",
      "sightSelling": "-"
    },
    {
      "currency": "CNY",
      "currencyZhTw": "人民幣",
      "cashBuying": "4.479",
      "cashSelling": "4.641",
      "sightBuying": "4.551",
      "sightSelling": "4.601"
    }
  ]
}